Metadata-Version: 1.1
Name: collective-dot
Version: 0.0.2
Summary: Validation Package
Home-page: https://github.com/MasoniteFramework/masonite
Author: Joseph Mancuso
Author-email: joe@masoniteproject.com
License: MIT
Keywords: masonite,python web framework,python3
Platform: UNKNOWN
Classifier: Development Status :: 3 - Alpha
Classifier: Intended Audience :: Developers
Classifier: Operating System :: OS Independent
Classifier: License :: OSI Approved :: MIT License
Classifier: Programming Language :: Python :: 3.4
Classifier: Programming Language :: Python :: 3.5
Classifier: Programming Language :: Python :: 3.6
Classifier: Programming Language :: Python :: 3.7
Classifier: Programming Language :: Python :: 3 :: Only
Classifier: Topic :: Software Development :: Libraries
Classifier: Topic :: Utilities
